nwws_oi_receiver-1.0.0.dist-info/licenses/LICENSE
nwws_receiver/__init__.py
nwws_receiver/config.py
nwws_receiver/message.py
nwws_receiver/py.typed
nwws_receiver/wx_wire.py
nwws_oi_receiver-1.0.0.dist-info/METADATA
nwws_oi_receiver-1.0.0.dist-info/WHEEL
nwws_oi_receiver-1.0.0.dist-info/top_level.txt
nwws_oi_receiver-1.0.0.dist-info/RECORD
