Metadata-Version: 2.4
Name: nwws-oi-receiver
Version: 1.0.0
Summary: Python implementation of the NWWS-OI XMPP protocol for receiving weather data
Author-email: Jonathan Bradshaw <jb@nrgup.net>
License-Expression: MIT
Project-URL: Homepage, https://github.com/bradsjm/nwws-oi-receiver
Project-URL: Documentation, https://github.com/bradsjm/nwws-oi-receiver/tree/main/docs
Project-URL: Repository, https://github.com/bradsjm/nwws-oi-receiver.git
Project-URL: Bug Tracker, https://github.com/bradsjm/nwws-oi-receiver/issues
Keywords: emwin,nwws,weather,noaa
Classifier: Development Status :: 5 - Production/Stable
Classifier: Intended Audience :: Developers
Classifier: Operating System :: OS Independent
Classifier: Programming Language :: Python :: 3
Classifier: Programming Language :: Python :: 3.12
Classifier: Programming Language :: Python :: 3.13
Classifier: Topic :: Communications
Classifier: Topic :: Scientific/Engineering :: Atmospheric Science
Classifier: Typing :: Typed
Requires-Python: >=3.12
License-File: LICENSE
Requires-Dist: slixmpp>=1.10.0
Provides-Extra: dev
Requires-Dist: ruff>=0.11.12; extra == "dev"
Dynamic: license-file
